django_textclassifier-1.0.dist-info/DESCRIPTION.rst
django_textclassifier-1.0.dist-info/METADATA
django_textclassifier-1.0.dist-info/metadata.json
django_textclassifier-1.0.dist-info/RECORD
django_textclassifier-1.0.dist-info/top_level.txt
django_textclassifier-1.0.dist-info/WHEEL
textclassifier/__init__.py
textclassifier/classifier.py
textclassifier/constants.py
textclassifier/validators.py
