Metadata-Version: 1.1
Name: django-textclassifier
Version: 1.0
Summary: Django text classifier validation
Home-page: http://github.com/agjohnson/django-textclassifier/
Author: Anthony Johnson
Author-email: aj@ohess.org
License: MIT License
Platform: any
Classifier: Development Status :: 4 - Beta
Classifier: Intended Audience :: Developers
Classifier: License :: OSI Approved :: MIT License
Classifier: Natural Language :: English
Classifier: Operating System :: OS Independent
Classifier: Programming Language :: Python
Classifier: Programming Language :: Python :: 2
Classifier: Programming Language :: Python :: 2.7
Classifier: Programming Language :: Python :: 3
Classifier: Programming Language :: Python :: 3.3
Classifier: Programming Language :: Python :: 3.4
Classifier: Environment :: Web Environment
